cubic_spline/__init__.py
cubic_spline/cubic_spline.py
cubic_spline/tools.py
cubic_spline-0.1.1.dist-info/LICENSE
cubic_spline-0.1.1.dist-info/METADATA
cubic_spline-0.1.1.dist-info/WHEEL
cubic_spline-0.1.1.dist-info/top_level.txt
cubic_spline-0.1.1.dist-info/RECORD
