Metadata-Version: 2.1
Name: cubic-spline
Version: 0.1.1
Summary: Cubic spline interpolation with Numba compatibility
Author-email: Harrison Snell <harrison.snell23@gmail.com>
Project-URL: Homepage, https://github.com/hwsnell/Cubic-Spline
Classifier: Programming Language :: Python :: 3
Classifier: License :: OSI Approved :: MIT License
Classifier: Operating System :: OS Independent
Requires-Python: >=3.7
License-File: LICENSE
